arcpyext/TopicCategory.py
arcpyext/__init__.py
arcpyext/_multiprocessing.py
arcpyext/_utils.py
arcpyext/_version.py
arcpyext/_json/__init__.py
arcpyext/_json/json_enum.py
arcpyext/_json/to_json_encoder.py
arcpyext/_native/__init__.py
arcpyext/_native/_dotnet.py
arcpyext/_native/arcgispro.py
arcpyext/_native/arcobjects.py
arcpyext/_patches/__init__.py
arcpyext/_patches/patches.py
arcpyext/_patches/_mp/CimEditor.py
arcpyext/_patches/_mp/Field.py
arcpyext/_patches/_mp/Layer.py
arcpyext/_patches/_mp/Map.py
arcpyext/_patches/_mp/Table.py
arcpyext/_patches/_mp/__init__.py
arcpyext/_patches/_mp/_cim_helpers.py
arcpyext/_patches/metadata/Metadata.py
arcpyext/_patches/metadata/__init__.py
arcpyext/_str/ExtendedFormatter.py
arcpyext/_str/__init__.py
arcpyext/_str/sql.py
arcpyext/_str/utils.py
arcpyext/conversion/ToCsv.py
arcpyext/conversion/ToGeoPackage.py
arcpyext/conversion/ToKml.py
arcpyext/conversion/ToMapInfoTab.py
arcpyext/conversion/ToOfficeOpenXmlWorkbook.py
arcpyext/conversion/ToShapefile.py
arcpyext/conversion/_ConvertBase.py
arcpyext/conversion/_ToCsvBase.py
arcpyext/conversion/__init__.py
arcpyext/conversion/_helpers.py
arcpyext/data/__init__.py
arcpyext/data/_data_management.py
arcpyext/exceptions/__init__.py
arcpyext/exceptions/arc_py_ext_error.py
arcpyext/exceptions/change_data_sources_error.py
arcpyext/exceptions/data_source_update_error.py
arcpyext/exceptions/map_data_sources_broken_error.py
arcpyext/exceptions/map_layer_error.py
arcpyext/exceptions/serv_def_draft_create_error.py
arcpyext/exceptions/unmapped_data_source_error.py
arcpyext/exceptions/unsupported_layer_error.py
arcpyext/mapping/__init__.py
arcpyext/mapping/_compare_helpers.py
arcpyext/mapping/_mapping.py
arcpyext/mapping/_mapping2.py
arcpyext/mapping/_mapping3.py
arcpyext/mapping/_mapping_helpers.py
arcpyext/mapping/compare_types.py
arcpyext/mapping/_cim/__init__.py
arcpyext/mapping/_cim/factories.py
arcpyext/mapping/_cim/helpers.py
arcpyext/mapping/_cim/layers.py
arcpyext-0.7.36.dist-info/LICENSE
arcpyext-0.7.36.dist-info/METADATA
arcpyext-0.7.36.dist-info/WHEEL
arcpyext-0.7.36.dist-info/top_level.txt
arcpyext-0.7.36.dist-info/RECORD
