Metadata-Version: 2.1
Name: arcpyext
Version: 0.7.36
Summary: Extended functionality for Esri's ArcPy site-package
Home-page: https://github.com/DavidWhittingham/arcpyext
Author: David Whittingham; David Payne; Adam Kerz; Peter Reyne; Daniel Baternik; Chris Blanchfield; Gary Bagnall
License: BSD 3-Clause
Keywords: arcgis esri arcpy
Classifier: Development Status :: 4 - Beta
Classifier: Intended Audience :: Developers
Classifier: Natural Language :: English
Classifier: License :: OSI Approved :: BSD License
Classifier: Programming Language :: Python
License-File: LICENSE
Requires-Dist: aenum <4,>=3.1.11
Requires-Dist: future >=0.18.2
Requires-Dist: pathlib2 <3,>=2.3.4
Requires-Dist: pythonnet <3,>=2.4.0 ; python_version < "3"
Requires-Dist: sqlparse <0.4,>=0.3.1 ; python_version < "3"
Requires-Dist: XlsxWriter <3,>=2 ; python_version < "3"
Requires-Dist: olefile ==0.47 ; python_version < "3.4"
Requires-Dist: pythonnet <4,>=3.0.0 ; python_version >= "3"
Requires-Dist: sqlparse <0.5,>=0.4.4 ; python_version >= "3"
Requires-Dist: XlsxWriter <4,>=3 ; python_version >= "3"
